COPYING.txt
MANIFEST.in
README.md
download.txt
setup.py
PyMunin.egg-info/PKG-INFO
PyMunin.egg-info/SOURCES.txt
PyMunin.egg-info/dependency_links.txt
PyMunin.egg-info/entry_points.txt
PyMunin.egg-info/top_level.txt
ext/apcinfo.php
ext/apache/status.conf
pymunin/__init__.py
pymunin/plugins/__init__.py
pymunin/plugins/apachestats.py
pymunin/plugins/asteriskstats.py
pymunin/plugins/diskiostats.py
pymunin/plugins/diskusagestats.py
pymunin/plugins/fsstats.py
pymunin/plugins/lighttpdstats.py
pymunin/plugins/memcachedstats.py
pymunin/plugins/mysqlstats.py
pymunin/plugins/netifacestats.py
pymunin/plugins/netstats.py
pymunin/plugins/nginxstats.py
pymunin/plugins/ntphostoffset_.py
pymunin/plugins/ntphostoffsets.py
pymunin/plugins/ntpstats.py
pymunin/plugins/pgstats.py
pymunin/plugins/phpapcstats.py
pymunin/plugins/phpfpmstats.py
pymunin/plugins/procstats.py
pymunin/plugins/rackspacestats.py
pymunin/plugins/redisstats.py
pymunin/plugins/sysstats.py
pymunin/plugins/tomcatstats.py
pymunin/plugins/varnishstats.py
pymunin/plugins/wanpipestats.py
pysysinfo/__init__.py
pysysinfo/apache.py
pysysinfo/asterisk.py
pysysinfo/diskio.py
pysysinfo/filesystem.py
pysysinfo/freeswitch.py
pysysinfo/lighttpd.py
pysysinfo/memcached.py
pysysinfo/mysql.py
pysysinfo/netiface.py
pysysinfo/netstat.py
pysysinfo/nginx.py
pysysinfo/ntp.py
pysysinfo/phpapc.py
pysysinfo/phpfpm.py
pysysinfo/postgresql.py
pysysinfo/process.py
pysysinfo/rackspace.py
pysysinfo/redisdb.py
pysysinfo/squid.py
pysysinfo/system.py
pysysinfo/tomcat.py
pysysinfo/util.py
pysysinfo/varnish.py
pysysinfo/wanpipe.py