Metadata-Version: 1.1
Name: PyMunin
Version: 0.9.27
Summary: Python Module for developing Munin Multigraph Monitoring Plugins.
Home-page: http://aouyar.github.com/PyMunin
Author: Ali Onur Uyar
Author-email: aouyar at gmail.com
License: GPL
Platform: UNKNOWN
Classifier: Topic :: System :: Monitoring
Classifier: Intended Audience :: Developers
Classifier: License :: OSI Approved :: GNU General Public License (GPL)
Classifier: Programming Language :: Python
Classifier: Topic :: Software Development :: Libraries :: Python Modules
Classifier: Development Status :: 4 - Beta
Classifier: Operating System :: OS Independent
